[
  {
    "theme": "bn_king_gap1_knight_controls_escape_all_light_bishops",
    "fen": "k7/8/1KN5/8/8/8/8/1B6 w - - 0 1",
    "black_king": "a8",
    "white_king": "b6",
    "white_knight": "c6",
    "white_bishop": "b1",
    "escape_squares_not_controlled_by_wk": [
      "b8"
    ]
  },
  {
    "theme": "bn_gap1_long_mates_with_engine",
    "fen": "k7/3N4/2K5/8/8/3B4/8/8 w - - 0 1",
    "black_king": "a8",
    "white_king": "c6",
    "white_knight": "d7",
    "white_bishop": "d3",
    "knight_controls_near_bk_squares": [
      "b8"
    ],
    "mate_distance": 5,
    "bestmove_uci": "d3a6",
    "bestmove_san": "Ba6"
  },
  {
    "theme": "bn_gap2_knight_controls_any_near_bk_square_all_light_bishops",
    "fen": "k1B5/8/3K4/2N5/8/8/8/8 w - - 0 1",
    "black_king": "a8",
    "white_king": "d6",
    "white_knight": "c5",
    "white_bishop": "c8",
    "knight_controls_near_bk_squares": [
      "b7"
    ]
  },
  {
    "theme": "bn_gap1_long_mates_with_engine",
    "fen": "k7/8/K7/2N5/8/1B6/8/8 w - - 0 1",
    "black_king": "a8",
    "white_king": "a6",
    "white_knight": "c5",
    "white_bishop": "b3",
    "knight_controls_near_bk_squares": [
      "b7"
    ],
    "mate_distance": 5,
    "bestmove_uci": "b3e6",
    "bestmove_san": "Be6"
  },
  {
    "theme": "bn_gap1_long_mates_with_engine",
    "fen": "k5B1/8/1K1N4/8/8/8/8/8 w - - 0 1",
    "black_king": "a8",
    "white_king": "b6",
    "white_knight": "d6",
    "white_bishop": "g8",
    "knight_controls_near_bk_squares": [
      "b7"
    ],
    "mate_distance": 5,
    "bestmove_uci": "g8e6",
    "bestmove_san": "Be6"
  },
  {
    "theme": "bn_gap1_long_mates_with_engine",
    "fen": "k7/8/2KN4/7B/8/8/8/8 w - - 0 1",
    "black_king": "a8",
    "white_king": "c6",
    "white_knight": "d6",
    "white_bishop": "h5",
    "knight_controls_near_bk_squares": [
      "b7"
    ],
    "mate_distance": 5,
    "bestmove_uci": "c6c7",
    "bestmove_san": "Kc7"
  },
  {
    "theme": "bn_gap2_knight_controls_any_near_bk_square_all_light_bishops",
    "fen": "k7/7B/8/1NK5/8/8/8/8 w - - 0 1",
    "black_king": "a8",
    "white_king": "c5",
    "white_knight": "b5",
    "white_bishop": "h7",
    "knight_controls_near_bk_squares": [
      "a7"
    ]
  },
  {
    "theme": "bn_gap1_long_mates_with_engine",
    "fen": "k7/8/K2N4/1B6/8/8/8/8 w - - 0 1",
    "black_king": "a8",
    "white_king": "a6",
    "white_knight": "d6",
    "white_bishop": "b5",
    "knight_controls_near_bk_squares": [
      "b7"
    ],
    "mate_distance": 6,
    "bestmove_uci": "a6b6",
    "bestmove_san": "Kb6"
  },
  {
    "theme": "bn_gap1_long_mates_with_engine",
    "fen": "k1K5/8/3N4/8/B7/8/8/8 w - - 0 1",
    "black_king": "a8",
    "white_king": "c8",
    "white_knight": "d6",
    "white_bishop": "a4",
    "knight_controls_near_bk_squares": [
      "b7"
    ],
    "mate_distance": 5,
    "bestmove_uci": "c8c7",
    "bestmove_san": "Kc7"
  },
  {
    "theme": "bn_gap1_long_mates_with_engine",
    "fen": "k3B3/2KN4/8/8/8/8/8/8 w - - 0 1",
    "black_king": "a8",
    "white_king": "c7",
    "white_knight": "d7",
    "white_bishop": "e8",
    "knight_controls_near_bk_squares": [
      "b8"
    ],
    "mate_distance": 5,
    "bestmove_uci": "e8g6",
    "bestmove_san": "Bg6"
  },
  {
    "theme": "bn_king_gap1_knight_controls_escape_all_light_bishops",
    "fen": "k7/8/K1N1B3/8/8/8/8/8 w - - 0 1",
    "black_king": "a8",
    "white_king": "a6",
    "white_knight": "c6",
    "white_bishop": "e6",
    "escape_squares_not_controlled_by_wk": [
      "b8"
    ]
  },
  {
    "theme": "bn_king_gap1_knight_controls_escape_all_light_bishops",
    "fen": "k7/8/1KN5/8/8/8/2B5/8 w - - 0 1",
    "black_king": "a8",
    "white_king": "b6",
    "white_knight": "c6",
    "white_bishop": "c2",
    "escape_squares_not_controlled_by_wk": [
      "b8"
    ]
  },
  {
    "theme": "bn_gap2_long_mates_with_engine",
    "fen": "k7/3N4/8/1K6/8/8/4B3/8 w - - 0 1",
    "black_king": "a8",
    "white_king": "b5",
    "white_knight": "d7",
    "white_bishop": "e2",
    "knight_controls_near_bk_squares": [
      "b8"
    ],
    "mate_distance": 7,
    "bestmove_uci": "b5c6",
    "bestmove_san": "Kc6"
  },
  {
    "theme": "bn_gap2_knight_controls_any_near_bk_square_all_light_bishops",
    "fen": "k7/8/8/K1N4B/8/8/8/8 w - - 0 1",
    "black_king": "a8",
    "white_king": "a5",
    "white_knight": "c5",
    "white_bishop": "h5",
    "knight_controls_near_bk_squares": [
      "b7"
    ]
  },
  {
    "theme": "bn_gap2_knight_controls_any_near_bk_square_all_light_bishops",
    "fen": "k7/8/8/2NK1B2/8/8/8/8 w - - 0 1",
    "black_king": "a8",
    "white_king": "d5",
    "white_knight": "c5",
    "white_bishop": "f5",
    "knight_controls_near_bk_squares": [
      "b7"
    ]
  },
  {
    "theme": "bn_gap2_knight_controls_any_near_bk_square_all_light_bishops",
    "fen": "k2N4/3B4/8/K7/8/8/8/8 w - - 0 1",
    "black_king": "a8",
    "white_king": "a5",
    "white_knight": "d8",
    "white_bishop": "d7",
    "knight_controls_near_bk_squares": [
      "b7"
    ]
  },
  {
    "theme": "bn_gap1_long_mates_with_engine",
    "fen": "k7/3N4/2K5/5B2/8/8/8/8 w - - 0 1",
    "black_king": "a8",
    "white_king": "c6",
    "white_knight": "d7",
    "white_bishop": "f5",
    "knight_controls_near_bk_squares": [
      "b8"
    ],
    "mate_distance": 5,
    "bestmove_uci": "d7c5",
    "bestmove_san": "Nc5"
  },
  {
    "theme": "bn_gap2_knight_controls_any_near_bk_square_all_light_bishops",
    "fen": "k7/3N4/3K4/8/8/8/4B3/8 w - - 0 1",
    "black_king": "a8",
    "white_king": "d6",
    "white_knight": "d7",
    "white_bishop": "e2",
    "knight_controls_near_bk_squares": [
      "b8"
    ]
  },
  {
    "theme": "bn_gap2_knight_controls_any_near_bk_square_all_light_bishops",
    "fen": "k2N4/3K4/8/1B6/8/8/8/8 w - - 0 1",
    "black_king": "a8",
    "white_king": "d7",
    "white_knight": "d8",
    "white_bishop": "b5",
    "knight_controls_near_bk_squares": [
      "b7"
    ]
  },
  {
    "theme": "bn_king_gap1_knight_controls_escape_all_light_bishops",
    "fen": "k7/2K5/2N5/8/8/1B6/8/8 w - - 0 1",
    "black_king": "a8",
    "white_king": "c7",
    "white_knight": "c6",
    "white_bishop": "b3",
    "escape_squares_not_controlled_by_wk": [
      "a7"
    ]
  },
  {
    "theme": "bn_gap2_knight_controls_any_near_bk_square_all_light_bishops",
    "fen": "k7/8/3K4/N7/8/8/4B3/8 w - - 0 1",
    "black_king": "a8",
    "white_king": "d6",
    "white_knight": "a5",
    "white_bishop": "e2",
    "knight_controls_near_bk_squares": [
      "b7"
    ]
  },
  {
    "theme": "bn_gap2_knight_controls_any_near_bk_square_all_light_bishops",
    "fen": "k7/8/N2K4/8/8/7B/8/8 w - - 0 1",
    "black_king": "a8",
    "white_king": "d6",
    "white_knight": "a6",
    "white_bishop": "h3",
    "knight_controls_near_bk_squares": [
      "b8"
    ]
  },
  {
    "theme": "bn_gap1_long_mates_with_engine",
    "fen": "k7/8/1K6/1N6/8/8/8/3B4 w - - 0 1",
    "black_king": "a8",
    "white_king": "b6",
    "white_knight": "b5",
    "white_bishop": "d1",
    "knight_controls_near_bk_squares": [
      "a7"
    ],
    "mate_distance": 5,
    "bestmove_uci": "d1g4",
    "bestmove_san": "Bg4"
  },
  {
    "theme": "bn_gap2_long_mates_with_engine",
    "fen": "k1B5/8/N7/1K6/8/8/8/8 w - - 0 1",
    "black_king": "a8",
    "white_king": "b5",
    "white_knight": "a6",
    "white_bishop": "c8",
    "knight_controls_near_bk_squares": [
      "b8"
    ],
    "mate_distance": 8,
    "bestmove_uci": "c8f5",
    "bestmove_san": "Bf5"
  },
  {
    "theme": "bn_gap1_long_mates_with_engine",
    "fen": "k1K5/3B4/N7/8/8/8/8/8 w - - 0 1",
    "black_king": "a8",
    "white_king": "c8",
    "white_knight": "a6",
    "white_bishop": "d7",
    "knight_controls_near_bk_squares": [
      "b8"
    ],
    "mate_distance": 5,
    "bestmove_uci": "a6b4",
    "bestmove_san": "Nb4"
  },
  {
    "theme": "bn_gap2_knight_controls_any_near_bk_square_all_light_bishops",
    "fen": "k2K4/3N4/6B1/8/8/8/8/8 w - - 0 1",
    "black_king": "a8",
    "white_king": "d8",
    "white_knight": "d7",
    "white_bishop": "g6",
    "knight_controls_near_bk_squares": [
      "b8"
    ]
  },
  {
    "theme": "bn_gap2_knight_controls_any_near_bk_square_all_light_bishops",
    "fen": "k5B1/8/3K4/2N5/8/8/8/8 w - - 0 1",
    "black_king": "a8",
    "white_king": "d6",
    "white_knight": "c5",
    "white_bishop": "g8",
    "knight_controls_near_bk_squares": [
      "b7"
    ]
  },
  {
    "theme": "bn_gap1_long_mates_with_engine",
    "fen": "k1K5/3N4/8/5B2/8/8/8/8 w - - 0 1",
    "black_king": "a8",
    "white_king": "c8",
    "white_knight": "d7",
    "white_bishop": "f5",
    "knight_controls_near_bk_squares": [
      "b8"
    ],
    "mate_distance": 5,
    "bestmove_uci": "c8c7",
    "bestmove_san": "Kc7"
  },
  {
    "theme": "bn_gap1_long_mates_with_engine",
    "fen": "k1K5/8/N7/8/6B1/8/8/8 w - - 0 1",
    "black_king": "a8",
    "white_king": "c8",
    "white_knight": "a6",
    "white_bishop": "g4",
    "knight_controls_near_bk_squares": [
      "b8"
    ],
    "mate_distance": 5,
    "bestmove_uci": "a6c5",
    "bestmove_san": "Nc5"
  }
]