[
  {
    "lichessId": "VvDXp",
    "fen": "3rr1k1/p4ppp/1p1p4/8/8/1Q1R1P2/P5PP/3Rq2K w - - 4 35",
    "moves": [
      "d1e1",
      "e8e1"
    ],
    "preMove": "d1e1",
    "solution": "e8e1",
    "theme": "mate_in_1",
    "subtheme": "back_rank",
    "rating": 421,
    "themes": [
      "backRankMate",
      "endgame",
      "mate",
      "mateIn1",
      "oneMove",
      "queenRookEndgame"
    ],
    "gameUrl": "https://lichess.org/nguQzNLS#69",
    "openingTags": [],
    "source": "lichess",
    "localId": "back_rank_chunk_142_puzzle_1",
    "chunk": 142,
    "chunkIndex": 0,
    "positionInChunk": 1
  },
  {
    "lichessId": "WBSEp",
    "fen": "r3Q1k1/pp3ppp/3r2q1/5b2/8/2N5/PPP1RPPP/2R3K1 b - - 12 22",
    "moves": [
      "a8e8",
      "e2e8"
    ],
    "preMove": "a8e8",
    "solution": "e2e8",
    "theme": "mate_in_1",
    "subtheme": "back_rank",
    "rating": 421,
    "themes": [
      "backRankMate",
      "mate",
      "mateIn1",
      "middlegame",
      "oneMove"
    ],
    "gameUrl": "https://lichess.org/nAR0aX7l/black#44",
    "openingTags": [],
    "source": "lichess",
    "localId": "back_rank_chunk_142_puzzle_2",
    "chunk": 142,
    "chunkIndex": 1,
    "positionInChunk": 2
  },
  {
    "lichessId": "WlsOg",
    "fen": "r4rk1/pp2n1bp/2n1R1p1/3P4/8/1B6/PP4PP/RNBQ1q1K w - - 2 16",
    "moves": [
      "d1f1",
      "f8f1"
    ],
    "preMove": "d1f1",
    "solution": "f8f1",
    "theme": "mate_in_1",
    "subtheme": "back_rank",
    "rating": 421,
    "themes": [
      "backRankMate",
      "mate",
      "mateIn1",
      "middlegame",
      "oneMove"
    ],
    "gameUrl": "https://lichess.org/Wi4j2dmj#31",
    "openingTags": [
      "Sicilian_Defense",
      "Sicilian_Defense_Old_Sicilian"
    ],
    "source": "lichess",
    "localId": "back_rank_chunk_142_puzzle_3",
    "chunk": 142,
    "chunkIndex": 2,
    "positionInChunk": 3
  },
  {
    "lichessId": "WwVlM",
    "fen": "r2r2k1/pp3ppp/2n5/5b2/Q4q2/4pN2/PP3PPP/K2R1B1R w - - 0 18",
    "moves": [
      "a4f4",
      "d8d1"
    ],
    "preMove": "a4f4",
    "solution": "d8d1",
    "theme": "mate_in_1",
    "subtheme": "back_rank",
    "rating": 421,
    "themes": [
      "backRankMate",
      "hangingPiece",
      "mate",
      "mateIn1",
      "middlegame",
      "oneMove"
    ],
    "gameUrl": "https://lichess.org/ewjsbrdX#35",
    "openingTags": [
      "Queens_Gambit_Declined",
      "Queens_Gambit_Declined_Semi-Tarrasch_Defense"
    ],
    "source": "lichess",
    "localId": "back_rank_chunk_142_puzzle_4",
    "chunk": 142,
    "chunkIndex": 3,
    "positionInChunk": 4
  },
  {
    "lichessId": "XfER2",
    "fen": "r1Q3k1/5ppp/p7/8/3pbB2/R7/1r4PP/2R4K b - - 2 31",
    "moves": [
      "a8c8",
      "c1c8"
    ],
    "preMove": "a8c8",
    "solution": "c1c8",
    "theme": "mate_in_1",
    "subtheme": "back_rank",
    "rating": 421,
    "themes": [
      "backRankMate",
      "endgame",
      "mate",
      "mateIn1",
      "oneMove"
    ],
    "gameUrl": "https://lichess.org/4wwkopE7/black#62",
    "openingTags": [],
    "source": "lichess",
    "localId": "back_rank_chunk_142_puzzle_5",
    "chunk": 142,
    "chunkIndex": 4,
    "positionInChunk": 5
  },
  {
    "lichessId": "YH2zj",
    "fen": "6k1/p1R2ppp/8/1B2n3/5P2/n5PP/8/7K b - - 0 31",
    "moves": [
      "a3b5",
      "c7c8"
    ],
    "preMove": "a3b5",
    "solution": "c7c8",
    "theme": "mate_in_1",
    "subtheme": "back_rank",
    "rating": 421,
    "themes": [
      "backRankMate",
      "endgame",
      "mate",
      "mateIn1",
      "oneMove"
    ],
    "gameUrl": "https://lichess.org/VruQrVqx/black#62",
    "openingTags": [],
    "source": "lichess",
    "localId": "back_rank_chunk_142_puzzle_6",
    "chunk": 142,
    "chunkIndex": 5,
    "positionInChunk": 6
  },
  {
    "lichessId": "Yg1Dc",
    "fen": "r3Q1k1/p4ppp/2pp4/3p4/3P1q2/2P1R3/PP3PPP/6K1 b - - 6 23",
    "moves": [
      "a8e8",
      "e3e8"
    ],
    "preMove": "a8e8",
    "solution": "e3e8",
    "theme": "mate_in_1",
    "subtheme": "back_rank",
    "rating": 421,
    "themes": [
      "backRankMate",
      "endgame",
      "mate",
      "mateIn1",
      "oneMove",
      "queenRookEndgame"
    ],
    "gameUrl": "https://lichess.org/XA7MRJRB/black#46",
    "openingTags": [],
    "source": "lichess",
    "localId": "back_rank_chunk_142_puzzle_7",
    "chunk": 142,
    "chunkIndex": 6,
    "positionInChunk": 7
  },
  {
    "lichessId": "YsWSe",
    "fen": "k1Q4r/pp2qppp/8/4P3/3r4/8/PP3PPP/2R2RK1 b - - 2 23",
    "moves": [
      "h8c8",
      "c1c8"
    ],
    "preMove": "h8c8",
    "solution": "c1c8",
    "theme": "mate_in_1",
    "subtheme": "back_rank",
    "rating": 421,
    "themes": [
      "backRankMate",
      "endgame",
      "mate",
      "mateIn1",
      "oneMove",
      "queenRookEndgame"
    ],
    "gameUrl": "https://lichess.org/GxsZi7Ey/black#46",
    "openingTags": [],
    "source": "lichess",
    "localId": "back_rank_chunk_142_puzzle_8",
    "chunk": 142,
    "chunkIndex": 7,
    "positionInChunk": 8
  },
  {
    "lichessId": "Yt8LR",
    "fen": "r1b2rk1/1p4pp/p1n5/6Q1/4p3/PNP5/2P3PP/R4q1K w - - 2 23",
    "moves": [
      "a1f1",
      "f8f1"
    ],
    "preMove": "a1f1",
    "solution": "f8f1",
    "theme": "mate_in_1",
    "subtheme": "back_rank",
    "rating": 421,
    "themes": [
      "backRankMate",
      "mate",
      "mateIn1",
      "middlegame",
      "oneMove"
    ],
    "gameUrl": "https://lichess.org/3AYtwTdG#45",
    "openingTags": [],
    "source": "lichess",
    "localId": "back_rank_chunk_142_puzzle_9",
    "chunk": 142,
    "chunkIndex": 8,
    "positionInChunk": 9
  },
  {
    "lichessId": "ZyQeY",
    "fen": "4rrk1/p6p/1p5R/2p1n1pQ/1PP1p3/P2pP3/6PP/2R2q1K w - - 0 35",
    "moves": [
      "c1f1",
      "f8f1"
    ],
    "preMove": "c1f1",
    "solution": "f8f1",
    "theme": "mate_in_1",
    "subtheme": "back_rank",
    "rating": 421,
    "themes": [
      "backRankMate",
      "endgame",
      "master",
      "mate",
      "mateIn1",
      "oneMove"
    ],
    "gameUrl": "https://lichess.org/4x5NZLd6#69",
    "openingTags": [],
    "source": "lichess",
    "localId": "back_rank_chunk_142_puzzle_10",
    "chunk": 142,
    "chunkIndex": 9,
    "positionInChunk": 10
  },
  {
    "lichessId": "aFjaZ",
    "fen": "2r3k1/pQ1n1pp1/P2Bp2p/4P3/3p4/8/5PPP/1Rq4K w - - 4 27",
    "moves": [
      "b1c1",
      "c8c1"
    ],
    "preMove": "b1c1",
    "solution": "c8c1",
    "theme": "mate_in_1",
    "subtheme": "back_rank",
    "rating": 421,
    "themes": [
      "backRankMate",
      "endgame",
      "mate",
      "mateIn1",
      "oneMove"
    ],
    "gameUrl": "https://lichess.org/MWLLGPmX#53",
    "openingTags": [],
    "source": "lichess",
    "localId": "back_rank_chunk_142_puzzle_11",
    "chunk": 142,
    "chunkIndex": 10,
    "positionInChunk": 11
  },
  {
    "lichessId": "b38zo",
    "fen": "1nb2rk1/5ppp/2p1pn2/2rp4/8/8/P2NPPPP/1R2KBNR w K - 4 14",
    "moves": [
      "b1b8",
      "c5c1"
    ],
    "preMove": "b1b8",
    "solution": "c5c1",
    "theme": "mate_in_1",
    "subtheme": "back_rank",
    "rating": 421,
    "themes": [
      "backRankMate",
      "mate",
      "mateIn1",
      "middlegame",
      "oneMove"
    ],
    "gameUrl": "https://lichess.org/CerEZguZ#27",
    "openingTags": [
      "Slav_Defense",
      "Slav_Defense_Other_variations"
    ],
    "source": "lichess",
    "localId": "back_rank_chunk_142_puzzle_12",
    "chunk": 142,
    "chunkIndex": 11,
    "positionInChunk": 12
  },
  {
    "lichessId": "bFCWE",
    "fen": "1k1Q3r/ppp5/8/8/2P5/3R3P/PP1pr1PK/3q4 b - - 3 37",
    "moves": [
      "h8d8",
      "d3d8"
    ],
    "preMove": "h8d8",
    "solution": "d3d8",
    "theme": "mate_in_1",
    "subtheme": "back_rank",
    "rating": 421,
    "themes": [
      "backRankMate",
      "endgame",
      "master",
      "mate",
      "mateIn1",
      "oneMove",
      "queenRookEndgame"
    ],
    "gameUrl": "https://lichess.org/jmRwW0bn/black#74",
    "openingTags": [],
    "source": "lichess",
    "localId": "back_rank_chunk_142_puzzle_13",
    "chunk": 142,
    "chunkIndex": 12,
    "positionInChunk": 13
  },
  {
    "lichessId": "cnCj2",
    "fen": "1n3rk1/1p4p1/pn5p/2p1P3/2P3B1/1PB4Q/P5PP/4Rq1K w - - 8 29",
    "moves": [
      "e1f1",
      "f8f1"
    ],
    "preMove": "e1f1",
    "solution": "f8f1",
    "theme": "mate_in_1",
    "subtheme": "back_rank",
    "rating": 421,
    "themes": [
      "backRankMate",
      "mate",
      "mateIn1",
      "middlegame",
      "oneMove"
    ],
    "gameUrl": "https://lichess.org/hngERQ4H#57",
    "openingTags": [],
    "source": "lichess",
    "localId": "back_rank_chunk_142_puzzle_14",
    "chunk": 142,
    "chunkIndex": 13,
    "positionInChunk": 14
  },
  {
    "lichessId": "dcnCz",
    "fen": "3r2k1/5p2/2R3p1/2p1n2p/2N5/b7/2P2PPP/6K1 w - - 1 24",
    "moves": [
      "c4e5",
      "d8d1"
    ],
    "preMove": "c4e5",
    "solution": "d8d1",
    "theme": "mate_in_1",
    "subtheme": "back_rank",
    "rating": 421,
    "themes": [
      "backRankMate",
      "endgame",
      "master",
      "mate",
      "mateIn1",
      "oneMove"
    ],
    "gameUrl": "https://lichess.org/MbUu1E2i#47",
    "openingTags": [],
    "source": "lichess",
    "localId": "back_rank_chunk_142_puzzle_15",
    "chunk": 142,
    "chunkIndex": 14,
    "positionInChunk": 15
  },
  {
    "lichessId": "eCTvE",
    "fen": "3q4/1Qp3kp/p3bp2/8/7B/8/PP3PPP/6K1 w - - 0 28",
    "moves": [
      "b2b3",
      "d8d1"
    ],
    "preMove": "b2b3",
    "solution": "d8d1",
    "theme": "mate_in_1",
    "subtheme": "back_rank",
    "rating": 421,
    "themes": [
      "backRankMate",
      "endgame",
      "mate",
      "mateIn1",
      "oneMove"
    ],
    "gameUrl": "https://lichess.org/9QJKHZTY#55",
    "openingTags": [],
    "source": "lichess",
    "localId": "back_rank_chunk_142_puzzle_16",
    "chunk": 142,
    "chunkIndex": 15,
    "positionInChunk": 16
  },
  {
    "lichessId": "eHpii",
    "fen": "1k2Q1r1/ppp3r1/8/3p3p/1B1P4/4Q2N/PP2KP1q/8 b - - 0 30",
    "moves": [
      "g8e8",
      "e3e8"
    ],
    "preMove": "g8e8",
    "solution": "e3e8",
    "theme": "mate_in_1",
    "subtheme": "back_rank",
    "rating": 421,
    "themes": [
      "backRankMate",
      "endgame",
      "mate",
      "mateIn1",
      "oneMove"
    ],
    "gameUrl": "https://lichess.org/uNKn2dcs/black#60",
    "openingTags": [],
    "source": "lichess",
    "localId": "back_rank_chunk_142_puzzle_17",
    "chunk": 142,
    "chunkIndex": 16,
    "positionInChunk": 17
  },
  {
    "lichessId": "f0pvX",
    "fen": "6k1/5p1p/2p3p1/2P1B3/2b1P3/1rP2P2/p5PP/R6K w - - 4 29",
    "moves": [
      "a1a2",
      "b3b1"
    ],
    "preMove": "a1a2",
    "solution": "b3b1",
    "theme": "mate_in_1",
    "subtheme": "back_rank",
    "rating": 421,
    "themes": [
      "backRankMate",
      "endgame",
      "mate",
      "mateIn1",
      "oneMove"
    ],
    "gameUrl": "https://lichess.org/qwnb2vaJ#57",
    "openingTags": [],
    "source": "lichess",
    "localId": "back_rank_chunk_142_puzzle_18",
    "chunk": 142,
    "chunkIndex": 17,
    "positionInChunk": 18
  },
  {
    "lichessId": "fNbaF",
    "fen": "8/1B3p1p/4p1pk/p3Q3/2P5/8/5rPP/R4q1K w - - 8 43",
    "moves": [
      "a1f1",
      "f2f1"
    ],
    "preMove": "a1f1",
    "solution": "f2f1",
    "theme": "mate_in_1",
    "subtheme": "back_rank",
    "rating": 421,
    "themes": [
      "backRankMate",
      "endgame",
      "mate",
      "mateIn1",
      "oneMove"
    ],
    "gameUrl": "https://lichess.org/bGqbF2TF#85",
    "openingTags": [],
    "source": "lichess",
    "localId": "back_rank_chunk_142_puzzle_19",
    "chunk": 142,
    "chunkIndex": 18,
    "positionInChunk": 19
  },
  {
    "lichessId": "gSUCf",
    "fen": "3Q3k/p4npp/6q1/4p3/6B1/P3P2P/2P3P1/5RK1 b - - 0 32",
    "moves": [
      "f7d8",
      "f1f8"
    ],
    "preMove": "f7d8",
    "solution": "f1f8",
    "theme": "mate_in_1",
    "subtheme": "back_rank",
    "rating": 421,
    "themes": [
      "backRankMate",
      "endgame",
      "mate",
      "mateIn1",
      "oneMove"
    ],
    "gameUrl": "https://lichess.org/eFqAesOg/black#64",
    "openingTags": [],
    "source": "lichess",
    "localId": "back_rank_chunk_142_puzzle_20",
    "chunk": 142,
    "chunkIndex": 19,
    "positionInChunk": 20
  },
  {
    "lichessId": "hMX0C",
    "fen": "rk1Q1b1r/ppp2Bpp/8/6q1/8/2N5/PP1R1PPP/2K3NR b - - 0 17",
    "moves": [
      "g5d8",
      "d2d8"
    ],
    "preMove": "g5d8",
    "solution": "d2d8",
    "theme": "mate_in_1",
    "subtheme": "back_rank",
    "rating": 421,
    "themes": [
      "backRankMate",
      "mate",
      "mateIn1",
      "middlegame",
      "oneMove"
    ],
    "gameUrl": "https://lichess.org/cB8GfCUO/black#34",
    "openingTags": [
      "French_Defense",
      "French_Defense_Orthoschnapp_Gambit"
    ],
    "source": "lichess",
    "localId": "back_rank_chunk_142_puzzle_21",
    "chunk": 142,
    "chunkIndex": 20,
    "positionInChunk": 21
  },
  {
    "lichessId": "hPkXS",
    "fen": "4r1k1/pq5p/5bp1/5p2/8/2PP1Q2/5PPP/6K1 w - - 0 26",
    "moves": [
      "f3b7",
      "e8e1"
    ],
    "preMove": "f3b7",
    "solution": "e8e1",
    "theme": "mate_in_1",
    "subtheme": "back_rank",
    "rating": 421,
    "themes": [
      "backRankMate",
      "endgame",
      "mate",
      "mateIn1",
      "oneMove"
    ],
    "gameUrl": "https://lichess.org/haC1Eh3L#51",
    "openingTags": [],
    "source": "lichess",
    "localId": "back_rank_chunk_142_puzzle_22",
    "chunk": 142,
    "chunkIndex": 21,
    "positionInChunk": 22
  },
  {
    "lichessId": "hYqJt",
    "fen": "4rrk1/2p3pp/p3b3/1p1pN3/8/1NP5/PPB3PP/R1BQ1q1K w - - 3 19",
    "moves": [
      "d1f1",
      "f8f1"
    ],
    "preMove": "d1f1",
    "solution": "f8f1",
    "theme": "mate_in_1",
    "subtheme": "back_rank",
    "rating": 421,
    "themes": [
      "backRankMate",
      "mate",
      "mateIn1",
      "middlegame",
      "oneMove"
    ],
    "gameUrl": "https://lichess.org/pfAQV298#37",
    "openingTags": [],
    "source": "lichess",
    "localId": "back_rank_chunk_142_puzzle_23",
    "chunk": 142,
    "chunkIndex": 22,
    "positionInChunk": 23
  },
  {
    "lichessId": "iWdCL",
    "fen": "2rQ3k/p5pp/b1p5/5p2/4p1q1/1P6/P5PP/2RR2K1 b - - 3 27",
    "moves": [
      "c8d8",
      "d1d8"
    ],
    "preMove": "c8d8",
    "solution": "d1d8",
    "theme": "mate_in_1",
    "subtheme": "back_rank",
    "rating": 421,
    "themes": [
      "backRankMate",
      "endgame",
      "mate",
      "mateIn1",
      "oneMove"
    ],
    "gameUrl": "https://lichess.org/hEQMdnrL/black#54",
    "openingTags": [],
    "source": "lichess",
    "localId": "back_rank_chunk_142_puzzle_24",
    "chunk": 142,
    "chunkIndex": 23,
    "positionInChunk": 24
  },
  {
    "lichessId": "k9EDZ",
    "fen": "k2r4/pp1Q2pp/5b2/2R5/8/7P/PPP2PP1/6K1 b - - 2 28",
    "moves": [
      "d8d7",
      "c5c8"
    ],
    "preMove": "d8d7",
    "solution": "c5c8",
    "theme": "mate_in_1",
    "subtheme": "back_rank",
    "rating": 421,
    "themes": [
      "backRankMate",
      "endgame",
      "mate",
      "mateIn1",
      "oneMove"
    ],
    "gameUrl": "https://lichess.org/pF1FWw3l/black#56",
    "openingTags": [],
    "source": "lichess",
    "localId": "back_rank_chunk_142_puzzle_25",
    "chunk": 142,
    "chunkIndex": 24,
    "positionInChunk": 25
  },
  {
    "lichessId": "kcKkZ",
    "fen": "7k/6pp/p2p4/1prPnp2/5Pb1/4R1K1/PP5P/8 b - - 0 32",
    "moves": [
      "e5c4",
      "e3e8"
    ],
    "preMove": "e5c4",
    "solution": "e3e8",
    "theme": "mate_in_1",
    "subtheme": "back_rank",
    "rating": 421,
    "themes": [
      "backRankMate",
      "endgame",
      "master",
      "mate",
      "mateIn1",
      "oneMove"
    ],
    "gameUrl": "https://lichess.org/1IqBSXMQ/black#64",
    "openingTags": [],
    "source": "lichess",
    "localId": "back_rank_chunk_142_puzzle_26",
    "chunk": 142,
    "chunkIndex": 25,
    "positionInChunk": 26
  },
  {
    "lichessId": "kdqgT",
    "fen": "r3r1k1/p4ppp/2pB4/2pp4/8/2NP1Q2/PPP2PPP/R3q1K1 w - - 1 18",
    "moves": [
      "a1e1",
      "e8e1"
    ],
    "preMove": "a1e1",
    "solution": "e8e1",
    "theme": "mate_in_1",
    "subtheme": "back_rank",
    "rating": 421,
    "themes": [
      "backRankMate",
      "endgame",
      "mate",
      "mateIn1",
      "oneMove"
    ],
    "gameUrl": "https://lichess.org/gqjb5tvr#35",
    "openingTags": [
      "Sicilian_Defense",
      "Sicilian_Defense_French_Variation"
    ],
    "source": "lichess",
    "localId": "back_rank_chunk_142_puzzle_27",
    "chunk": 142,
    "chunkIndex": 26,
    "positionInChunk": 27
  },
  {
    "lichessId": "l35rk",
    "fen": "r1b3k1/1p3ppp/p3p3/8/8/2P1P3/P2rBPPP/2RR2K1 b - - 0 17",
    "moves": [
      "d2e2",
      "d1d8"
    ],
    "preMove": "d2e2",
    "solution": "d1d8",
    "theme": "mate_in_1",
    "subtheme": "back_rank",
    "rating": 421,
    "themes": [
      "backRankMate",
      "endgame",
      "mate",
      "mateIn1",
      "oneMove"
    ],
    "gameUrl": "https://lichess.org/KupCyysz/black#34",
    "openingTags": [
      "Queens_Gambit_Declined",
      "Queens_Gambit_Declined_Semi-Tarrasch_Defense"
    ],
    "source": "lichess",
    "localId": "back_rank_chunk_142_puzzle_28",
    "chunk": 142,
    "chunkIndex": 27,
    "positionInChunk": 28
  },
  {
    "lichessId": "lAqak",
    "fen": "4rrk1/p1p3pp/2p5/2b2b2/8/4NB2/PPP3PP/R1B4K w - - 2 18",
    "moves": [
      "e3f5",
      "e8e1"
    ],
    "preMove": "e3f5",
    "solution": "e8e1",
    "theme": "mate_in_1",
    "subtheme": "back_rank",
    "rating": 421,
    "themes": [
      "backRankMate",
      "mate",
      "mateIn1",
      "middlegame",
      "oneMove"
    ],
    "gameUrl": "https://lichess.org/UxWHjjDi#35",
    "openingTags": [
      "Scotch_Game",
      "Scotch_Game_Other_variations"
    ],
    "source": "lichess",
    "localId": "back_rank_chunk_142_puzzle_29",
    "chunk": 142,
    "chunkIndex": 28,
    "positionInChunk": 29
  },
  {
    "lichessId": "lCm8Q",
    "fen": "8/1p6/pk1r3p/8/4pRP1/4R2P/PPP5/K5n1 w - - 5 43",
    "moves": [
      "f4e4",
      "d6d1"
    ],
    "preMove": "f4e4",
    "solution": "d6d1",
    "theme": "mate_in_1",
    "subtheme": "back_rank",
    "rating": 421,
    "themes": [
      "backRankMate",
      "endgame",
      "master",
      "mate",
      "mateIn1",
      "oneMove"
    ],
    "gameUrl": "https://lichess.org/5T4hJcG3#85",
    "openingTags": [],
    "source": "lichess",
    "localId": "back_rank_chunk_142_puzzle_30",
    "chunk": 142,
    "chunkIndex": 29,
    "positionInChunk": 30
  }
]