[
  {
    "lichessId": "R7nPt",
    "fen": "r4rk1/pp4pp/2n1b3/2P1p2Q/8/2N5/P5PP/R1B1Rq1K w - - 2 20",
    "moves": [
      "e1f1",
      "f8f1"
    ],
    "preMove": "e1f1",
    "solution": "f8f1",
    "theme": "mate_in_1",
    "subtheme": "back_rank",
    "rating": 399,
    "themes": [
      "backRankMate",
      "mate",
      "mateIn1",
      "middlegame",
      "oneMove"
    ],
    "gameUrl": "https://lichess.org/HXKl59B1#39",
    "openingTags": [],
    "source": "lichess",
    "localId": "back_rank_chunk_22_puzzle_1",
    "chunk": 22,
    "chunkIndex": 0,
    "positionInChunk": 1
  },
  {
    "lichessId": "RA3B9",
    "fen": "1k2r3/ppp2ppp/8/8/8/1P3P2/1KP1R2P/3R4 b - - 0 26",
    "moves": [
      "e8e2",
      "d1d8"
    ],
    "preMove": "e8e2",
    "solution": "d1d8",
    "theme": "mate_in_1",
    "subtheme": "back_rank",
    "rating": 399,
    "themes": [
      "backRankMate",
      "endgame",
      "mate",
      "mateIn1",
      "oneMove",
      "rookEndgame"
    ],
    "gameUrl": "https://lichess.org/D3rM9o4C/black#52",
    "openingTags": [],
    "source": "lichess",
    "localId": "back_rank_chunk_22_puzzle_2",
    "chunk": 22,
    "chunkIndex": 1,
    "positionInChunk": 2
  },
  {
    "lichessId": "RCKrI",
    "fen": "r4rk1/ppR1R1pp/2b3p1/3p4/N7/1P6/P5PP/3Q1q1K w - - 2 23",
    "moves": [
      "d1f1",
      "f8f1"
    ],
    "preMove": "d1f1",
    "solution": "f8f1",
    "theme": "mate_in_1",
    "subtheme": "back_rank",
    "rating": 399,
    "themes": [
      "backRankMate",
      "mate",
      "mateIn1",
      "middlegame",
      "oneMove"
    ],
    "gameUrl": "https://lichess.org/EAenwnYy#45",
    "openingTags": [],
    "source": "lichess",
    "localId": "back_rank_chunk_22_puzzle_3",
    "chunk": 22,
    "chunkIndex": 2,
    "positionInChunk": 3
  },
  {
    "lichessId": "RCrFP",
    "fen": "r3k2r/1ppbqp2/1p1p4/1P2p1p1/2P1P2p/3K1PP1/3N1B1P/R2R4 b kq - 0 26",
    "moves": [
      "e8c8",
      "a1a8"
    ],
    "preMove": "e8c8",
    "solution": "a1a8",
    "theme": "mate_in_1",
    "subtheme": "back_rank",
    "rating": 399,
    "themes": [
      "backRankMate",
      "mate",
      "mateIn1",
      "middlegame",
      "oneMove"
    ],
    "gameUrl": "https://lichess.org/mrdPihUK/black#52",
    "openingTags": [],
    "source": "lichess",
    "localId": "back_rank_chunk_22_puzzle_4",
    "chunk": 22,
    "chunkIndex": 3,
    "positionInChunk": 4
  },
  {
    "lichessId": "RHkKR",
    "fen": "2q2Q1k/6pp/8/P3r3/1P6/2P1b1PP/6K1/R4R2 b - - 2 26",
    "moves": [
      "c8f8",
      "f1f8"
    ],
    "preMove": "c8f8",
    "solution": "f1f8",
    "theme": "mate_in_1",
    "subtheme": "back_rank",
    "rating": 399,
    "themes": [
      "backRankMate",
      "endgame",
      "mate",
      "mateIn1",
      "oneMove"
    ],
    "gameUrl": "https://lichess.org/nZJYyj6n/black#52",
    "openingTags": [],
    "source": "lichess",
    "localId": "back_rank_chunk_22_puzzle_5",
    "chunk": 22,
    "chunkIndex": 4,
    "positionInChunk": 5
  },
  {
    "lichessId": "RJCJY",
    "fen": "1rb1r2k/1p1p1pp1/p2P3p/8/8/5Q2/PPR2PPP/2R1q2K w - - 2 29",
    "moves": [
      "c1e1",
      "e8e1"
    ],
    "preMove": "c1e1",
    "solution": "e8e1",
    "theme": "mate_in_1",
    "subtheme": "back_rank",
    "rating": 399,
    "themes": [
      "backRankMate",
      "endgame",
      "mate",
      "mateIn1",
      "oneMove"
    ],
    "gameUrl": "https://lichess.org/aKNWmwUp#57",
    "openingTags": [],
    "source": "lichess",
    "localId": "back_rank_chunk_22_puzzle_6",
    "chunk": 22,
    "chunkIndex": 5,
    "positionInChunk": 6
  },
  {
    "lichessId": "RJbTL",
    "fen": "2r3k1/5ppp/8/3pRpb1/3P4/2R4P/6PB/6K1 b - - 0 29",
    "moves": [
      "c8c3",
      "e5e8"
    ],
    "preMove": "c8c3",
    "solution": "e5e8",
    "theme": "mate_in_1",
    "subtheme": "back_rank",
    "rating": 399,
    "themes": [
      "backRankMate",
      "endgame",
      "mate",
      "mateIn1",
      "oneMove"
    ],
    "gameUrl": "https://lichess.org/efeJPOOo/black#58",
    "openingTags": [],
    "source": "lichess",
    "localId": "back_rank_chunk_22_puzzle_7",
    "chunk": 22,
    "chunkIndex": 6,
    "positionInChunk": 7
  },
  {
    "lichessId": "RK74P",
    "fen": "r6k/2p2Rpp/p2p4/1p1Bp3/1P2P3/2PPb2P/P6K/8 b - - 1 22",
    "moves": [
      "a8a7",
      "f7f8"
    ],
    "preMove": "a8a7",
    "solution": "f7f8",
    "theme": "mate_in_1",
    "subtheme": "back_rank",
    "rating": 399,
    "themes": [
      "backRankMate",
      "endgame",
      "mate",
      "mateIn1",
      "oneMove"
    ],
    "gameUrl": "https://lichess.org/nK8Tn3kg/black#44",
    "openingTags": [],
    "source": "lichess",
    "localId": "back_rank_chunk_22_puzzle_8",
    "chunk": 22,
    "chunkIndex": 7,
    "positionInChunk": 8
  },
  {
    "lichessId": "ROyLj",
    "fen": "r5k1/pp4p1/2n1p2p/5r2/8/PQ1p4/P2B2PP/R4q1K w - - 2 23",
    "moves": [
      "a1f1",
      "f5f1"
    ],
    "preMove": "a1f1",
    "solution": "f5f1",
    "theme": "mate_in_1",
    "subtheme": "back_rank",
    "rating": 399,
    "themes": [
      "backRankMate",
      "endgame",
      "mate",
      "mateIn1",
      "oneMove"
    ],
    "gameUrl": "https://lichess.org/I1KaHyIA#45",
    "openingTags": [],
    "source": "lichess",
    "localId": "back_rank_chunk_22_puzzle_9",
    "chunk": 22,
    "chunkIndex": 8,
    "positionInChunk": 9
  },
  {
    "lichessId": "RPZ9i",
    "fen": "k2r4/p3Qpp1/1pp5/8/8/8/PPP5/1K1qR3 w - - 4 34",
    "moves": [
      "e1d1",
      "d8d1"
    ],
    "preMove": "e1d1",
    "solution": "d8d1",
    "theme": "mate_in_1",
    "subtheme": "back_rank",
    "rating": 399,
    "themes": [
      "backRankMate",
      "endgame",
      "mate",
      "mateIn1",
      "oneMove",
      "queenRookEndgame"
    ],
    "gameUrl": "https://lichess.org/b4BMfTV0#67",
    "openingTags": [],
    "source": "lichess",
    "localId": "back_rank_chunk_22_puzzle_10",
    "chunk": 22,
    "chunkIndex": 9,
    "positionInChunk": 10
  },
  {
    "lichessId": "RYtzi",
    "fen": "r2Q1k2/4nppp/7n/3RP3/5P2/6PP/PPP5/2K5 b - - 4 33",
    "moves": [
      "a8d8",
      "d5d8"
    ],
    "preMove": "a8d8",
    "solution": "d5d8",
    "theme": "mate_in_1",
    "subtheme": "back_rank",
    "rating": 399,
    "themes": [
      "backRankMate",
      "endgame",
      "master",
      "mate",
      "mateIn1",
      "oneMove"
    ],
    "gameUrl": "https://lichess.org/uZOFbAho/black#66",
    "openingTags": [],
    "source": "lichess",
    "localId": "back_rank_chunk_22_puzzle_11",
    "chunk": 22,
    "chunkIndex": 10,
    "positionInChunk": 11
  },
  {
    "lichessId": "Rb9Ht",
    "fen": "4r3/5B1k/6p1/p3R2p/P7/1P3Q2/5PPP/4q1K1 w - - 1 30",
    "moves": [
      "e5e1",
      "e8e1"
    ],
    "preMove": "e5e1",
    "solution": "e8e1",
    "theme": "mate_in_1",
    "subtheme": "back_rank",
    "rating": 399,
    "themes": [
      "backRankMate",
      "endgame",
      "mate",
      "mateIn1",
      "oneMove"
    ],
    "gameUrl": "https://lichess.org/t8zj2kik#59",
    "openingTags": [],
    "source": "lichess",
    "localId": "back_rank_chunk_22_puzzle_12",
    "chunk": 22,
    "chunkIndex": 11,
    "positionInChunk": 12
  },
  {
    "lichessId": "RdzoT",
    "fen": "3r4/pp2n1pp/4kp2/8/4N3/P5B1/1b3PPP/1R4K1 w - - 0 20",
    "moves": [
      "b1b2",
      "d8d1"
    ],
    "preMove": "b1b2",
    "solution": "d8d1",
    "theme": "mate_in_1",
    "subtheme": "back_rank",
    "rating": 399,
    "themes": [
      "backRankMate",
      "endgame",
      "mate",
      "mateIn1",
      "oneMove"
    ],
    "gameUrl": "https://lichess.org/abRU92Eh#39",
    "openingTags": [],
    "source": "lichess",
    "localId": "back_rank_chunk_22_puzzle_13",
    "chunk": 22,
    "chunkIndex": 12,
    "positionInChunk": 13
  },
  {
    "lichessId": "RfTKj",
    "fen": "3r2k1/p4p1p/1p4p1/8/8/1P3P2/4Q1PP/2Bq3K w - - 1 32",
    "moves": [
      "e2d1",
      "d8d1"
    ],
    "preMove": "e2d1",
    "solution": "d8d1",
    "theme": "mate_in_1",
    "subtheme": "back_rank",
    "rating": 399,
    "themes": [
      "backRankMate",
      "endgame",
      "mate",
      "mateIn1",
      "oneMove"
    ],
    "gameUrl": "https://lichess.org/n5oJUugw#63",
    "openingTags": [],
    "source": "lichess",
    "localId": "back_rank_chunk_22_puzzle_14",
    "chunk": 22,
    "chunkIndex": 13,
    "positionInChunk": 14
  },
  {
    "lichessId": "RgLrC",
    "fen": "k1Q1q3/pp4p1/7p/3P4/8/8/PB4PP/2R3K1 b - - 2 31",
    "moves": [
      "e8c8",
      "c1c8"
    ],
    "preMove": "e8c8",
    "solution": "c1c8",
    "theme": "mate_in_1",
    "subtheme": "back_rank",
    "rating": 399,
    "themes": [
      "backRankMate",
      "endgame",
      "mate",
      "mateIn1",
      "oneMove"
    ],
    "gameUrl": "https://lichess.org/mDFHgTQX/black#62",
    "openingTags": [],
    "source": "lichess",
    "localId": "back_rank_chunk_22_puzzle_15",
    "chunk": 22,
    "chunkIndex": 14,
    "positionInChunk": 15
  },
  {
    "lichessId": "RgTRu",
    "fen": "4R3/3k1p1p/p1pp3Q/8/P7/8/2P3PP/1r5K w - - 1 37",
    "moves": [
      "e8e1",
      "b1e1"
    ],
    "preMove": "e8e1",
    "solution": "b1e1",
    "theme": "mate_in_1",
    "subtheme": "back_rank",
    "rating": 399,
    "themes": [
      "backRankMate",
      "endgame",
      "hangingPiece",
      "mate",
      "mateIn1",
      "oneMove",
      "queenRookEndgame"
    ],
    "gameUrl": "https://lichess.org/U8Q0NLnn#73",
    "openingTags": [],
    "source": "lichess",
    "localId": "back_rank_chunk_22_puzzle_16",
    "chunk": 22,
    "chunkIndex": 15,
    "positionInChunk": 16
  },
  {
    "lichessId": "RhVFr",
    "fen": "6k1/5ppp/p7/r3p3/P7/6PP/2R2PK1/8 b - - 1 36",
    "moves": [
      "a5a4",
      "c2c8"
    ],
    "preMove": "a5a4",
    "solution": "c2c8",
    "theme": "mate_in_1",
    "subtheme": "back_rank",
    "rating": 399,
    "themes": [
      "backRankMate",
      "endgame",
      "master",
      "mate",
      "mateIn1",
      "oneMove",
      "rookEndgame"
    ],
    "gameUrl": "https://lichess.org/HJBvJve2/black#72",
    "openingTags": [],
    "source": "lichess",
    "localId": "back_rank_chunk_22_puzzle_17",
    "chunk": 22,
    "chunkIndex": 16,
    "positionInChunk": 17
  },
  {
    "lichessId": "Rj4I5",
    "fen": "r3Q1k1/p4ppp/2p5/3p3b/8/5N1P/PPq2PP1/R3R1K1 b - - 1 18",
    "moves": [
      "a8e8",
      "e1e8"
    ],
    "preMove": "a8e8",
    "solution": "e1e8",
    "theme": "mate_in_1",
    "subtheme": "back_rank",
    "rating": 399,
    "themes": [
      "backRankMate",
      "endgame",
      "mate",
      "mateIn1",
      "oneMove"
    ],
    "gameUrl": "https://lichess.org/63rVeaON/black#36",
    "openingTags": [
      "Sicilian_Defense",
      "Sicilian_Defense_Marshall_Counterattack"
    ],
    "source": "lichess",
    "localId": "back_rank_chunk_22_puzzle_18",
    "chunk": 22,
    "chunkIndex": 17,
    "positionInChunk": 18
  },
  {
    "lichessId": "RjAps",
    "fen": "5r2/6kp/6p1/1p1pn3/8/1P6/2P3PP/4R2K w - - 0 33",
    "moves": [
      "e1e5",
      "f8f1"
    ],
    "preMove": "e1e5",
    "solution": "f8f1",
    "theme": "mate_in_1",
    "subtheme": "back_rank",
    "rating": 399,
    "themes": [
      "backRankMate",
      "endgame",
      "mate",
      "mateIn1",
      "oneMove",
      "rookEndgame"
    ],
    "gameUrl": "https://lichess.org/yqvDxX0B#65",
    "openingTags": [],
    "source": "lichess",
    "localId": "back_rank_chunk_22_puzzle_19",
    "chunk": 22,
    "chunkIndex": 18,
    "positionInChunk": 19
  },
  {
    "lichessId": "RjFg1",
    "fen": "4rQ1k/2pp2pp/p7/1p6/4q3/2P3B1/PP4PP/5R1K b - - 2 24",
    "moves": [
      "e8f8",
      "f1f8"
    ],
    "preMove": "e8f8",
    "solution": "f1f8",
    "theme": "mate_in_1",
    "subtheme": "back_rank",
    "rating": 399,
    "themes": [
      "backRankMate",
      "endgame",
      "mate",
      "mateIn1",
      "oneMove"
    ],
    "gameUrl": "https://lichess.org/NiYiNBLJ/black#48",
    "openingTags": [],
    "source": "lichess",
    "localId": "back_rank_chunk_22_puzzle_20",
    "chunk": 22,
    "chunkIndex": 19,
    "positionInChunk": 20
  },
  {
    "lichessId": "Rkjmn",
    "fen": "r1b3k1/ppp2ppp/1n6/8/1P2P3/PB1rpN2/6PP/3RR1K1 b - - 3 18",
    "moves": [
      "d3b3",
      "d1d8"
    ],
    "preMove": "d3b3",
    "solution": "d1d8",
    "theme": "mate_in_1",
    "subtheme": "back_rank",
    "rating": 399,
    "themes": [
      "backRankMate",
      "mate",
      "mateIn1",
      "middlegame",
      "oneMove"
    ],
    "gameUrl": "https://lichess.org/GLRPgHlZ/black#36",
    "openingTags": [
      "Queens_Gambit_Declined",
      "Queens_Gambit_Declined_Marshall_Defense"
    ],
    "source": "lichess",
    "localId": "back_rank_chunk_22_puzzle_21",
    "chunk": 22,
    "chunkIndex": 20,
    "positionInChunk": 21
  },
  {
    "lichessId": "Rq1t5",
    "fen": "8/3R2pk/pR5p/8/8/8/PP6/K3q3 w - - 1 40",
    "moves": [
      "d7d1",
      "e1d1"
    ],
    "preMove": "d7d1",
    "solution": "e1d1",
    "theme": "mate_in_1",
    "subtheme": "back_rank",
    "rating": 399,
    "themes": [
      "backRankMate",
      "endgame",
      "hangingPiece",
      "mate",
      "mateIn1",
      "oneMove",
      "queenRookEndgame"
    ],
    "gameUrl": "https://lichess.org/f2vaWHpP#79",
    "openingTags": [],
    "source": "lichess",
    "localId": "back_rank_chunk_22_puzzle_22",
    "chunk": 22,
    "chunkIndex": 21,
    "positionInChunk": 22
  },
  {
    "lichessId": "Rq5Vm",
    "fen": "r2Q1k1r/p3nppp/p1p3b1/8/1q2P3/2N2N2/PP4PP/2KR3R b - - 3 16",
    "moves": [
      "a8d8",
      "d1d8"
    ],
    "preMove": "a8d8",
    "solution": "d1d8",
    "theme": "mate_in_1",
    "subtheme": "back_rank",
    "rating": 399,
    "themes": [
      "backRankMate",
      "mate",
      "mateIn1",
      "middlegame",
      "oneMove"
    ],
    "gameUrl": "https://lichess.org/FeY7e25Z/black#32",
    "openingTags": [
      "Queens_Gambit_Declined",
      "Queens_Gambit_Declined_Other_variations"
    ],
    "source": "lichess",
    "localId": "back_rank_chunk_22_puzzle_23",
    "chunk": 22,
    "chunkIndex": 22,
    "positionInChunk": 23
  },
  {
    "lichessId": "Rz3ZS",
    "fen": "6k1/p4pp1/4p2p/2q1P3/2Q5/8/P2r1PPP/6K1 w - - 0 27",
    "moves": [
      "c4c5",
      "d2d1"
    ],
    "preMove": "c4c5",
    "solution": "d2d1",
    "theme": "mate_in_1",
    "subtheme": "back_rank",
    "rating": 399,
    "themes": [
      "backRankMate",
      "endgame",
      "mate",
      "mateIn1",
      "oneMove",
      "queenRookEndgame"
    ],
    "gameUrl": "https://lichess.org/dVNz6ny8#53",
    "openingTags": [],
    "source": "lichess",
    "localId": "back_rank_chunk_22_puzzle_24",
    "chunk": 22,
    "chunkIndex": 23,
    "positionInChunk": 24
  },
  {
    "lichessId": "RzQAF",
    "fen": "5R1k/5rpp/8/p7/P3P3/7P/3q2PB/5R1K b - - 0 35",
    "moves": [
      "f7f8",
      "f1f8"
    ],
    "preMove": "f7f8",
    "solution": "f1f8",
    "theme": "mate_in_1",
    "subtheme": "back_rank",
    "rating": 399,
    "themes": [
      "backRankMate",
      "endgame",
      "mate",
      "mateIn1",
      "oneMove"
    ],
    "gameUrl": "https://lichess.org/2oWibjzL/black#70",
    "openingTags": [],
    "source": "lichess",
    "localId": "back_rank_chunk_22_puzzle_25",
    "chunk": 22,
    "chunkIndex": 24,
    "positionInChunk": 25
  },
  {
    "lichessId": "RzkOT",
    "fen": "r3r1k1/ppp2pp1/7B/3p4/6Q1/8/P4PPP/b2Rq1K1 w - - 1 25",
    "moves": [
      "d1e1",
      "e8e1"
    ],
    "preMove": "d1e1",
    "solution": "e8e1",
    "theme": "mate_in_1",
    "subtheme": "back_rank",
    "rating": 399,
    "themes": [
      "backRankMate",
      "endgame",
      "mate",
      "mateIn1",
      "oneMove"
    ],
    "gameUrl": "https://lichess.org/WaU1H8QZ#49",
    "openingTags": [],
    "source": "lichess",
    "localId": "back_rank_chunk_22_puzzle_26",
    "chunk": 22,
    "chunkIndex": 25,
    "positionInChunk": 26
  },
  {
    "lichessId": "S1eeC",
    "fen": "r4Q1k/pp4pp/2p5/3p4/B7/6P1/Pqb3PP/5R1K b - - 3 25",
    "moves": [
      "a8f8",
      "f1f8"
    ],
    "preMove": "a8f8",
    "solution": "f1f8",
    "theme": "mate_in_1",
    "subtheme": "back_rank",
    "rating": 399,
    "themes": [
      "backRankMate",
      "endgame",
      "mate",
      "mateIn1",
      "oneMove"
    ],
    "gameUrl": "https://lichess.org/baXFFY1x/black#50",
    "openingTags": [],
    "source": "lichess",
    "localId": "back_rank_chunk_22_puzzle_27",
    "chunk": 22,
    "chunkIndex": 26,
    "positionInChunk": 27
  },
  {
    "lichessId": "S2g2m",
    "fen": "1k6/ppp2p2/3p1p1r/4p3/4P3/2P2P2/PP4Rp/2KB4 b - - 0 25",
    "moves": [
      "h2h1q",
      "g2g8"
    ],
    "preMove": "h2h1q",
    "solution": "g2g8",
    "theme": "mate_in_1",
    "subtheme": "back_rank",
    "rating": 399,
    "themes": [
      "backRankMate",
      "endgame",
      "mate",
      "mateIn1",
      "oneMove"
    ],
    "gameUrl": "https://lichess.org/uywViplx/black#50",
    "openingTags": [],
    "source": "lichess",
    "localId": "back_rank_chunk_22_puzzle_28",
    "chunk": 22,
    "chunkIndex": 27,
    "positionInChunk": 28
  },
  {
    "lichessId": "S2jiJ",
    "fen": "3r2k1/1p3ppp/p7/8/8/1P6/1P3PPP/3rR1K1 w - - 0 24",
    "moves": [
      "e1d1",
      "d8d1"
    ],
    "preMove": "e1d1",
    "solution": "d8d1",
    "theme": "mate_in_1",
    "subtheme": "back_rank",
    "rating": 399,
    "themes": [
      "backRankMate",
      "endgame",
      "mate",
      "mateIn1",
      "oneMove",
      "rookEndgame"
    ],
    "gameUrl": "https://lichess.org/t8rKKfRf#47",
    "openingTags": [],
    "source": "lichess",
    "localId": "back_rank_chunk_22_puzzle_29",
    "chunk": 22,
    "chunkIndex": 28,
    "positionInChunk": 29
  },
  {
    "lichessId": "S3ILJ",
    "fen": "5k2/6pp/5p2/2P5/1P1r4/2q5/6PP/2R4K w - - 0 39",
    "moves": [
      "c1c3",
      "d4d1"
    ],
    "preMove": "c1c3",
    "solution": "d4d1",
    "theme": "mate_in_1",
    "subtheme": "back_rank",
    "rating": 399,
    "themes": [
      "backRankMate",
      "endgame",
      "mate",
      "mateIn1",
      "oneMove",
      "rookEndgame"
    ],
    "gameUrl": "https://lichess.org/41P6O6dv#77",
    "openingTags": [],
    "source": "lichess",
    "localId": "back_rank_chunk_22_puzzle_30",
    "chunk": 22,
    "chunkIndex": 29,
    "positionInChunk": 30
  }
]