[
  {
    "lichessId": "4sVyV",
    "fen": "r4r1k/pp4pp/4B3/8/8/PQP5/6PP/R4q1K w - - 2 24",
    "moves": [
      "a1f1",
      "f8f1"
    ],
    "preMove": "a1f1",
    "solution": "f8f1",
    "theme": "mate_in_1",
    "subtheme": "back_rank",
    "rating": 405,
    "themes": [
      "backRankMate",
      "endgame",
      "master",
      "mate",
      "mateIn1",
      "oneMove"
    ],
    "gameUrl": "https://lichess.org/HQy5OawX#47",
    "openingTags": [],
    "source": "lichess",
    "localId": "back_rank_chunk_96_puzzle_1",
    "chunk": 96,
    "chunkIndex": 0,
    "positionInChunk": 1
  },
  {
    "lichessId": "5MoUG",
    "fen": "rn2rQ1k/pp1q2pp/2p5/3nP1B1/3P4/2P3P1/P5BP/R4RK1 b - - 4 18",
    "moves": [
      "e8f8",
      "f1f8"
    ],
    "preMove": "e8f8",
    "solution": "f1f8",
    "theme": "mate_in_1",
    "subtheme": "back_rank",
    "rating": 405,
    "themes": [
      "backRankMate",
      "mate",
      "mateIn1",
      "middlegame",
      "oneMove"
    ],
    "gameUrl": "https://lichess.org/P2Y5fTic/black#36",
    "openingTags": [
      "Kings_Pawn_Game",
      "Kings_Pawn_Game_Other_variations"
    ],
    "source": "lichess",
    "localId": "back_rank_chunk_96_puzzle_2",
    "chunk": 96,
    "chunkIndex": 1,
    "positionInChunk": 2
  },
  {
    "lichessId": "5QpsE",
    "fen": "4r1k1/p4pp1/2p2n1p/3p4/8/2N2P2/PQ4PP/1R2q2K w - - 4 29",
    "moves": [
      "b1e1",
      "e8e1"
    ],
    "preMove": "b1e1",
    "solution": "e8e1",
    "theme": "mate_in_1",
    "subtheme": "back_rank",
    "rating": 405,
    "themes": [
      "backRankMate",
      "endgame",
      "mate",
      "mateIn1",
      "oneMove"
    ],
    "gameUrl": "https://lichess.org/T1qAmrLE#57",
    "openingTags": [],
    "source": "lichess",
    "localId": "back_rank_chunk_96_puzzle_3",
    "chunk": 96,
    "chunkIndex": 2,
    "positionInChunk": 3
  },
  {
    "lichessId": "6A5dx",
    "fen": "R3r3/3k1ppp/p1p5/P4p2/2P5/8/1P3PPP/6K1 w - - 3 32",
    "moves": [
      "a8a6",
      "e8e1"
    ],
    "preMove": "a8a6",
    "solution": "e8e1",
    "theme": "mate_in_1",
    "subtheme": "back_rank",
    "rating": 405,
    "themes": [
      "backRankMate",
      "endgame",
      "mate",
      "mateIn1",
      "oneMove",
      "rookEndgame"
    ],
    "gameUrl": "https://lichess.org/ZlFGwpuD#63",
    "openingTags": [],
    "source": "lichess",
    "localId": "back_rank_chunk_96_puzzle_4",
    "chunk": 96,
    "chunkIndex": 3,
    "positionInChunk": 4
  },
  {
    "lichessId": "6bkRc",
    "fen": "4Q2k/p5pp/3b4/P7/1P1N4/2r4q/4KR2/8 b - - 2 37",
    "moves": [
      "d6f8",
      "f2f8"
    ],
    "preMove": "d6f8",
    "solution": "f2f8",
    "theme": "mate_in_1",
    "subtheme": "back_rank",
    "rating": 405,
    "themes": [
      "backRankMate",
      "endgame",
      "hangingPiece",
      "mate",
      "mateIn1",
      "oneMove"
    ],
    "gameUrl": "https://lichess.org/txYhumcr/black#74",
    "openingTags": [],
    "source": "lichess",
    "localId": "back_rank_chunk_96_puzzle_5",
    "chunk": 96,
    "chunkIndex": 4,
    "positionInChunk": 5
  },
  {
    "lichessId": "7r3Of",
    "fen": "8/pp4kp/5rp1/3r4/2p5/2P5/PP4PP/3R3K w - - 0 36",
    "moves": [
      "d1d5",
      "f6f1"
    ],
    "preMove": "d1d5",
    "solution": "f6f1",
    "theme": "mate_in_1",
    "subtheme": "back_rank",
    "rating": 405,
    "themes": [
      "backRankMate",
      "endgame",
      "mate",
      "mateIn1",
      "oneMove",
      "rookEndgame"
    ],
    "gameUrl": "https://lichess.org/y5NVJgH0#71",
    "openingTags": [],
    "source": "lichess",
    "localId": "back_rank_chunk_96_puzzle_6",
    "chunk": 96,
    "chunkIndex": 5,
    "positionInChunk": 6
  },
  {
    "lichessId": "8UxUX",
    "fen": "6k1/pp3ppp/2p5/P7/4R3/2PpP1P1/1r2rPKP/5R2 b - - 3 33",
    "moves": [
      "d3d2",
      "e4e8"
    ],
    "preMove": "d3d2",
    "solution": "e4e8",
    "theme": "mate_in_1",
    "subtheme": "back_rank",
    "rating": 405,
    "themes": [
      "backRankMate",
      "endgame",
      "mate",
      "mateIn1",
      "oneMove",
      "rookEndgame"
    ],
    "gameUrl": "https://lichess.org/s8LEednA/black#66",
    "openingTags": [],
    "source": "lichess",
    "localId": "back_rank_chunk_96_puzzle_7",
    "chunk": 96,
    "chunkIndex": 6,
    "positionInChunk": 7
  },
  {
    "lichessId": "Ce5LD",
    "fen": "r4r2/pbp4k/4R2p/3p4/2p5/2P4Q/P1P3PP/R4q1K w - - 2 23",
    "moves": [
      "a1f1",
      "f8f1"
    ],
    "preMove": "a1f1",
    "solution": "f8f1",
    "theme": "mate_in_1",
    "subtheme": "back_rank",
    "rating": 405,
    "themes": [
      "backRankMate",
      "endgame",
      "mate",
      "mateIn1",
      "oneMove"
    ],
    "gameUrl": "https://lichess.org/gylc9CQz#45",
    "openingTags": [],
    "source": "lichess",
    "localId": "back_rank_chunk_96_puzzle_8",
    "chunk": 96,
    "chunkIndex": 7,
    "positionInChunk": 8
  },
  {
    "lichessId": "Cenue",
    "fen": "R5k1/1r3ppp/4p3/3pPn2/8/5N2/1P1K1PPP/8 b - - 1 22",
    "moves": [
      "b7b8",
      "a8b8"
    ],
    "preMove": "b7b8",
    "solution": "a8b8",
    "theme": "mate_in_1",
    "subtheme": "back_rank",
    "rating": 405,
    "themes": [
      "backRankMate",
      "endgame",
      "hangingPiece",
      "mate",
      "mateIn1",
      "oneMove"
    ],
    "gameUrl": "https://lichess.org/7qQkVfXc/black#44",
    "openingTags": [],
    "source": "lichess",
    "localId": "back_rank_chunk_96_puzzle_9",
    "chunk": 96,
    "chunkIndex": 8,
    "positionInChunk": 9
  },
  {
    "lichessId": "Dxiu4",
    "fen": "4r1k1/5pp1/3q1b1p/p4Q2/8/1P6/P4PPP/3R2K1 w - - 0 27",
    "moves": [
      "d1d6",
      "e8e1"
    ],
    "preMove": "d1d6",
    "solution": "e8e1",
    "theme": "mate_in_1",
    "subtheme": "back_rank",
    "rating": 405,
    "themes": [
      "backRankMate",
      "endgame",
      "mate",
      "mateIn1",
      "oneMove"
    ],
    "gameUrl": "https://lichess.org/5pAsbJsR#53",
    "openingTags": [],
    "source": "lichess",
    "localId": "back_rank_chunk_96_puzzle_10",
    "chunk": 96,
    "chunkIndex": 9,
    "positionInChunk": 10
  },
  {
    "lichessId": "FmzfD",
    "fen": "r1bq2k1/ppp2ppp/3p4/4Q1PP/1n2P3/2N5/PPP1B3/2KR2NR b - - 0 18",
    "moves": [
      "d6e5",
      "d1d8"
    ],
    "preMove": "d6e5",
    "solution": "d1d8",
    "theme": "mate_in_1",
    "subtheme": "back_rank",
    "rating": 405,
    "themes": [
      "backRankMate",
      "hangingPiece",
      "mate",
      "mateIn1",
      "middlegame",
      "oneMove"
    ],
    "gameUrl": "https://lichess.org/KXkwpknk/black#36",
    "openingTags": [
      "Nimzowitsch_Defense",
      "Nimzowitsch_Defense_Kennedy_Variation"
    ],
    "source": "lichess",
    "localId": "back_rank_chunk_96_puzzle_11",
    "chunk": 96,
    "chunkIndex": 10,
    "positionInChunk": 11
  },
  {
    "lichessId": "IVaNY",
    "fen": "5rk1/pp1Q1Rp1/8/b1p1P3/3P3N/2P5/PP4PP/4q2K w - - 1 31",
    "moves": [
      "f7f1",
      "f8f1"
    ],
    "preMove": "f7f1",
    "solution": "f8f1",
    "theme": "mate_in_1",
    "subtheme": "back_rank",
    "rating": 405,
    "themes": [
      "backRankMate",
      "endgame",
      "hangingPiece",
      "mate",
      "mateIn1",
      "oneMove"
    ],
    "gameUrl": "https://lichess.org/G6ROv9wL#61",
    "openingTags": [],
    "source": "lichess",
    "localId": "back_rank_chunk_96_puzzle_12",
    "chunk": 96,
    "chunkIndex": 11,
    "positionInChunk": 12
  },
  {
    "lichessId": "J0wzH",
    "fen": "3r2k1/pp3ppp/8/3Q4/8/6P1/PP3P1P/4R1K1 b - - 0 24",
    "moves": [
      "d8d5",
      "e1e8"
    ],
    "preMove": "d8d5",
    "solution": "e1e8",
    "theme": "mate_in_1",
    "subtheme": "back_rank",
    "rating": 405,
    "themes": [
      "backRankMate",
      "endgame",
      "mate",
      "mateIn1",
      "oneMove",
      "rookEndgame"
    ],
    "gameUrl": "https://lichess.org/vJnxmIcZ/black#48",
    "openingTags": [],
    "source": "lichess",
    "localId": "back_rank_chunk_96_puzzle_13",
    "chunk": 96,
    "chunkIndex": 12,
    "positionInChunk": 13
  },
  {
    "lichessId": "JV0sn",
    "fen": "5r1k/ppp3pp/2Q5/8/3pp3/8/PP4PP/2B1Rr1K w - - 1 30",
    "moves": [
      "e1f1",
      "f8f1"
    ],
    "preMove": "e1f1",
    "solution": "f8f1",
    "theme": "mate_in_1",
    "subtheme": "back_rank",
    "rating": 405,
    "themes": [
      "backRankMate",
      "endgame",
      "mate",
      "mateIn1",
      "oneMove"
    ],
    "gameUrl": "https://lichess.org/vmi9KA0h#59",
    "openingTags": [],
    "source": "lichess",
    "localId": "back_rank_chunk_96_puzzle_14",
    "chunk": 96,
    "chunkIndex": 13,
    "positionInChunk": 14
  },
  {
    "lichessId": "Ksxvt",
    "fen": "3r3k/1R4Rp/2p2n2/p7/6N1/b5P1/6PP/7K w - - 1 38",
    "moves": [
      "g4f6",
      "d8d1"
    ],
    "preMove": "g4f6",
    "solution": "d8d1",
    "theme": "mate_in_1",
    "subtheme": "back_rank",
    "rating": 405,
    "themes": [
      "backRankMate",
      "endgame",
      "mate",
      "mateIn1",
      "oneMove"
    ],
    "gameUrl": "https://lichess.org/wEubNyKn#75",
    "openingTags": [],
    "source": "lichess",
    "localId": "back_rank_chunk_96_puzzle_15",
    "chunk": 96,
    "chunkIndex": 14,
    "positionInChunk": 15
  },
  {
    "lichessId": "LHVLn",
    "fen": "r1b1qQ1k/ppp3pp/8/3np3/3P4/8/PP4PP/RNB2RK1 b - - 0 19",
    "moves": [
      "e8f8",
      "f1f8"
    ],
    "preMove": "e8f8",
    "solution": "f1f8",
    "theme": "mate_in_1",
    "subtheme": "back_rank",
    "rating": 405,
    "themes": [
      "backRankMate",
      "mate",
      "mateIn1",
      "middlegame",
      "oneMove"
    ],
    "gameUrl": "https://lichess.org/8M9LfVWt/black#38",
    "openingTags": [],
    "source": "lichess",
    "localId": "back_rank_chunk_96_puzzle_16",
    "chunk": 96,
    "chunkIndex": 15,
    "positionInChunk": 16
  },
  {
    "lichessId": "M842Z",
    "fen": "r1bQ1rk1/pp3ppp/8/2p5/4P3/8/PKP2PPP/3R1B1R b - - 0 13",
    "moves": [
      "f8d8",
      "d1d8"
    ],
    "preMove": "f8d8",
    "solution": "d1d8",
    "theme": "mate_in_1",
    "subtheme": "back_rank",
    "rating": 405,
    "themes": [
      "backRankMate",
      "endgame",
      "mate",
      "mateIn1",
      "oneMove"
    ],
    "gameUrl": "https://lichess.org/OqMzkitC/black#26",
    "openingTags": [
      "Scotch_Game",
      "Scotch_Game_Lolli_Variation"
    ],
    "source": "lichess",
    "localId": "back_rank_chunk_96_puzzle_17",
    "chunk": 96,
    "chunkIndex": 16,
    "positionInChunk": 17
  },
  {
    "lichessId": "Md4bh",
    "fen": "6Qk/pp1R1ppp/4p3/6B1/2q5/8/P4PPP/6K1 b - - 0 23",
    "moves": [
      "h8g8",
      "d7d8"
    ],
    "preMove": "h8g8",
    "solution": "d7d8",
    "theme": "mate_in_1",
    "subtheme": "back_rank",
    "rating": 405,
    "themes": [
      "backRankMate",
      "endgame",
      "mate",
      "mateIn1",
      "oneMove"
    ],
    "gameUrl": "https://lichess.org/ejLNsmx7/black#46",
    "openingTags": [],
    "source": "lichess",
    "localId": "back_rank_chunk_96_puzzle_18",
    "chunk": 96,
    "chunkIndex": 17,
    "positionInChunk": 18
  },
  {
    "lichessId": "N5uY5",
    "fen": "1k2Rb1r/ppp2ppp/8/8/3r1n2/2N2N2/PPP2PPP/2KR4 b - - 0 15",
    "moves": [
      "d4d8",
      "d1d8"
    ],
    "preMove": "d4d8",
    "solution": "d1d8",
    "theme": "mate_in_1",
    "subtheme": "back_rank",
    "rating": 405,
    "themes": [
      "backRankMate",
      "hangingPiece",
      "mate",
      "mateIn1",
      "middlegame",
      "oneMove"
    ],
    "gameUrl": "https://lichess.org/5EH8rArY/black#30",
    "openingTags": [
      "Four_Knights_Game",
      "Four_Knights_Game_Spanish_Variation"
    ],
    "source": "lichess",
    "localId": "back_rank_chunk_96_puzzle_19",
    "chunk": 96,
    "chunkIndex": 18,
    "positionInChunk": 19
  },
  {
    "lichessId": "NPlsO",
    "fen": "1k2Q2r/ppp3p1/8/5P2/3P4/2P1RPqr/PP5p/4R2K b - - 2 31",
    "moves": [
      "h8e8",
      "e3e8"
    ],
    "preMove": "h8e8",
    "solution": "e3e8",
    "theme": "mate_in_1",
    "subtheme": "back_rank",
    "rating": 405,
    "themes": [
      "backRankMate",
      "endgame",
      "mate",
      "mateIn1",
      "oneMove",
      "queenRookEndgame"
    ],
    "gameUrl": "https://lichess.org/IsuqujXK/black#62",
    "openingTags": [],
    "source": "lichess",
    "localId": "back_rank_chunk_96_puzzle_20",
    "chunk": 96,
    "chunkIndex": 19,
    "positionInChunk": 20
  },
  {
    "lichessId": "OKlOI",
    "fen": "5r1k/pR3pp1/2N1p2p/8/2P5/8/P4QPP/2q1r2K w - - 0 33",
    "moves": [
      "f2e1",
      "c1e1"
    ],
    "preMove": "f2e1",
    "solution": "c1e1",
    "theme": "mate_in_1",
    "subtheme": "back_rank",
    "rating": 405,
    "themes": [
      "backRankMate",
      "endgame",
      "hangingPiece",
      "mate",
      "mateIn1",
      "oneMove"
    ],
    "gameUrl": "https://lichess.org/fFzqJgpv#65",
    "openingTags": [],
    "source": "lichess",
    "localId": "back_rank_chunk_96_puzzle_21",
    "chunk": 96,
    "chunkIndex": 20,
    "positionInChunk": 21
  },
  {
    "lichessId": "OR1CT",
    "fen": "1Q1q2k1/p4ppp/2p1p3/2P5/8/P7/5PPP/1R1b2K1 b - - 2 30",
    "moves": [
      "d8b8",
      "b1b8"
    ],
    "preMove": "d8b8",
    "solution": "b1b8",
    "theme": "mate_in_1",
    "subtheme": "back_rank",
    "rating": 405,
    "themes": [
      "backRankMate",
      "endgame",
      "mate",
      "mateIn1",
      "oneMove"
    ],
    "gameUrl": "https://lichess.org/VRVLHhAv/black#60",
    "openingTags": [],
    "source": "lichess",
    "localId": "back_rank_chunk_96_puzzle_22",
    "chunk": 96,
    "chunkIndex": 21,
    "positionInChunk": 22
  },
  {
    "lichessId": "Pkdzr",
    "fen": "rnbk4/ppp3pp/8/2b5/4Br1N/8/PPPP2PP/RNB2RK1 w - - 1 12",
    "moves": [
      "g1h1",
      "f4f1"
    ],
    "preMove": "g1h1",
    "solution": "f4f1",
    "theme": "mate_in_1",
    "subtheme": "back_rank",
    "rating": 405,
    "themes": [
      "backRankMate",
      "hangingPiece",
      "mate",
      "mateIn1",
      "oneMove",
      "opening"
    ],
    "gameUrl": "https://lichess.org/5enKcVvo#23",
    "openingTags": [
      "Petrovs_Defense",
      "Petrovs_Defense_Italian_Variation"
    ],
    "source": "lichess",
    "localId": "back_rank_chunk_96_puzzle_23",
    "chunk": 96,
    "chunkIndex": 22,
    "positionInChunk": 23
  },
  {
    "lichessId": "Pvkuo",
    "fen": "2b1Rq1k/p2Q2pp/1p6/8/8/1P6/P1P2PPP/6K1 b - - 3 29",
    "moves": [
      "c8d7",
      "e8f8"
    ],
    "preMove": "c8d7",
    "solution": "e8f8",
    "theme": "mate_in_1",
    "subtheme": "back_rank",
    "rating": 405,
    "themes": [
      "backRankMate",
      "endgame",
      "hangingPiece",
      "mate",
      "mateIn1",
      "oneMove"
    ],
    "gameUrl": "https://lichess.org/r3CHk2A2/black#58",
    "openingTags": [],
    "source": "lichess",
    "localId": "back_rank_chunk_96_puzzle_24",
    "chunk": 96,
    "chunkIndex": 23,
    "positionInChunk": 24
  },
  {
    "lichessId": "RnNfQ",
    "fen": "6k1/p4ppp/2N1p3/8/8/q7/5PPP/2Q3K1 w - - 0 32",
    "moves": [
      "c6e5",
      "a3c1"
    ],
    "preMove": "c6e5",
    "solution": "a3c1",
    "theme": "mate_in_1",
    "subtheme": "back_rank",
    "rating": 405,
    "themes": [
      "backRankMate",
      "endgame",
      "hangingPiece",
      "mate",
      "mateIn1",
      "oneMove"
    ],
    "gameUrl": "https://lichess.org/3yJYWSY2#63",
    "openingTags": [],
    "source": "lichess",
    "localId": "back_rank_chunk_96_puzzle_25",
    "chunk": 96,
    "chunkIndex": 24,
    "positionInChunk": 25
  },
  {
    "lichessId": "TFPam",
    "fen": "2r2rk1/5pp1/p3p2p/1p2P3/4R2Q/PP4R1/1P4PP/2q4K w - - 3 31",
    "moves": [
      "e4e1",
      "c1e1"
    ],
    "preMove": "e4e1",
    "solution": "c1e1",
    "theme": "mate_in_1",
    "subtheme": "back_rank",
    "rating": 405,
    "themes": [
      "backRankMate",
      "endgame",
      "hangingPiece",
      "mate",
      "mateIn1",
      "oneMove"
    ],
    "gameUrl": "https://lichess.org/XFZHVaGg#61",
    "openingTags": [],
    "source": "lichess",
    "localId": "back_rank_chunk_96_puzzle_26",
    "chunk": 96,
    "chunkIndex": 25,
    "positionInChunk": 26
  },
  {
    "lichessId": "UFM9w",
    "fen": "2k2Qr1/pqppp2p/1p1b4/3P4/N1P5/1P2n1P1/P6P/R4RK1 b - - 2 23",
    "moves": [
      "g8f8",
      "f1f8"
    ],
    "preMove": "g8f8",
    "solution": "f1f8",
    "theme": "mate_in_1",
    "subtheme": "back_rank",
    "rating": 405,
    "themes": [
      "backRankMate",
      "mate",
      "mateIn1",
      "middlegame",
      "oneMove"
    ],
    "gameUrl": "https://lichess.org/G69gUxkd/black#46",
    "openingTags": [],
    "source": "lichess",
    "localId": "back_rank_chunk_96_puzzle_27",
    "chunk": 96,
    "chunkIndex": 26,
    "positionInChunk": 27
  },
  {
    "lichessId": "WHz6C",
    "fen": "1k6/ppp2RK1/6P1/8/PP5q/2P5/8/8 b - - 12 48",
    "moves": [
      "h4g3",
      "f7f8"
    ],
    "preMove": "h4g3",
    "solution": "f7f8",
    "theme": "mate_in_1",
    "subtheme": "back_rank",
    "rating": 405,
    "themes": [
      "backRankMate",
      "endgame",
      "mate",
      "mateIn1",
      "oneMove",
      "queenRookEndgame"
    ],
    "gameUrl": "https://lichess.org/8G6Vux25/black#96",
    "openingTags": [],
    "source": "lichess",
    "localId": "back_rank_chunk_96_puzzle_28",
    "chunk": 96,
    "chunkIndex": 27,
    "positionInChunk": 28
  },
  {
    "lichessId": "Wu3fu",
    "fen": "3r2k1/pQ3pp1/4pbp1/8/1Pq5/P7/5PPP/2R3K1 w - - 0 24",
    "moves": [
      "c1c4",
      "d8d1"
    ],
    "preMove": "c1c4",
    "solution": "d8d1",
    "theme": "mate_in_1",
    "subtheme": "back_rank",
    "rating": 405,
    "themes": [
      "backRankMate",
      "endgame",
      "mate",
      "mateIn1",
      "oneMove"
    ],
    "gameUrl": "https://lichess.org/C1vXIZ16#47",
    "openingTags": [],
    "source": "lichess",
    "localId": "back_rank_chunk_96_puzzle_29",
    "chunk": 96,
    "chunkIndex": 28,
    "positionInChunk": 29
  },
  {
    "lichessId": "XMhuA",
    "fen": "3R4/p3pp1p/5kp1/8/8/4P3/Pr3PPP/6K1 w - - 0 24",
    "moves": [
      "d8a8",
      "b2b1"
    ],
    "preMove": "d8a8",
    "solution": "b2b1",
    "theme": "mate_in_1",
    "subtheme": "back_rank",
    "rating": 405,
    "themes": [
      "backRankMate",
      "endgame",
      "master",
      "mate",
      "mateIn1",
      "oneMove",
      "rookEndgame"
    ],
    "gameUrl": "https://lichess.org/zaWqXRWv#47",
    "openingTags": [],
    "source": "lichess",
    "localId": "back_rank_chunk_96_puzzle_30",
    "chunk": 96,
    "chunkIndex": 29,
    "positionInChunk": 30
  }
]