[
  {
    "lichess_id": "000rZ",
    "fen": "2kr1b1r/p1p2pp1/2pqb3/7p/3N2n1/2NPB3/PPP2PPP/R2Q1RK1 w - - 2 13",
    "solution_move": "d4e6",
    "full_solution": "d4e6 d6h2",
    "subtheme": "matein1",
    "chunk_number": 1,
    "position_in_chunk": 1
  },
  {
    "lichess_id": "001KR",
    "fen": "6Qk/p1p3pp/4N3/1p6/2q1r1n1/2B5/PP4PP/3R1R1K b - - 0 28",
    "solution_move": "h8g8",
    "full_solution": "h8g8 f1f8",
    "subtheme": "matein1",
    "chunk_number": 1,
    "position_in_chunk": 2
  },
  {
    "lichess_id": "001cr",
    "fen": "8/3B2pp/p5k1/2p3P1/1p1p1K2/8/1P6/8 b - - 0 38",
    "solution_move": "c5c4",
    "full_solution": "c5c4 d7e8",
    "subtheme": "matein1",
    "chunk_number": 1,
    "position_in_chunk": 3
  },
  {
    "lichess_id": "001gi",
    "fen": "r6r/1pNk1ppp/2np4/b3p3/4P1b1/N1Q5/P4PPP/R3KB1R w KQ - 3 18",
    "solution_move": "c7a8",
    "full_solution": "c7a8 a5c3",
    "subtheme": "matein1",
    "chunk_number": 1,
    "position_in_chunk": 4
  },
  {
    "lichess_id": "001pC",
    "fen": "r4rk1/pp3ppp/3b4/2p1pPB1/7N/2PP3n/PP4PP/R2Q1RqK w - - 5 18",
    "solution_move": "f1g1",
    "full_solution": "f1g1 h3f2",
    "subtheme": "matein1",
    "chunk_number": 1,
    "position_in_chunk": 5
  },
  {
    "lichess_id": "001wb",
    "fen": "r3k2r/pb1p1ppp/1b4q1/1Q2P3/8/2NP1Pn1/PP4PP/R1B2R1K w kq - 1 17",
    "solution_move": "h2g3",
    "full_solution": "h2g3 g6h5",
    "subtheme": "matein1",
    "chunk_number": 1,
    "position_in_chunk": 6
  },
  {
    "lichess_id": "002CP",
    "fen": "r5k1/pp4pp/4p1q1/4p3/3n4/P5P1/1PP2Q1P/2KR1R2 w - - 4 24",
    "solution_move": "f2e3",
    "full_solution": "f2e3 g6c2",
    "subtheme": "matein1",
    "chunk_number": 1,
    "position_in_chunk": 7
  },
  {
    "lichess_id": "002HE",
    "fen": "1qr2rk1/1p1p1ppp/pB2p1n1/7n/2P1P3/1Q2NP1P/PP2B1Pb/3R1RK1 w - - 1 20",
    "solution_move": "g1f2",
    "full_solution": "g1f2 b8g3",
    "subtheme": "matein1",
    "chunk_number": 1,
    "position_in_chunk": 8
  },
  {
    "lichess_id": "002Q2",
    "fen": "7k/p4R1p/3p3r/2pN1n2/2PbBBb1/3P2P1/P3r3/5R1K w - - 1 28",
    "solution_move": "f4h6",
    "full_solution": "f4h6 f5g3",
    "subtheme": "matein1",
    "chunk_number": 1,
    "position_in_chunk": 9
  },
  {
    "lichess_id": "002Z9",
    "fen": "4r1k1/1p2R1p1/p2p2Pp/P1pP4/5q2/1R3p2/1P1Q3P/5B1K b - - 0 34",
    "solution_move": "f4d2",
    "full_solution": "f4d2 e7e8",
    "subtheme": "matein1",
    "chunk_number": 1,
    "position_in_chunk": 10
  },
  {
    "lichess_id": "002vV",
    "fen": "8/6k1/2R4p/5p1P/5P1K/6P1/8/r7 w - - 2 58",
    "solution_move": "c6b6",
    "full_solution": "c6b6 a1h1",
    "subtheme": "matein1",
    "chunk_number": 1,
    "position_in_chunk": 11
  },
  {
    "lichess_id": "003AX",
    "fen": "2r2rk1/5ppp/bq2p3/p1ppP1N1/Pb1P2P1/1P2P2P/2QN4/2R1K2R b K - 1 18",
    "solution_move": "c5d4",
    "full_solution": "c5d4 c2h7",
    "subtheme": "matein1",
    "chunk_number": 1,
    "position_in_chunk": 12
  },
  {
    "lichess_id": "003IX",
    "fen": "8/3pk3/R7/1R2Pp1p/2PPnKr1/8/8/8 w - - 4 43",
    "solution_move": "f4f5",
    "full_solution": "f4f5 e4g3",
    "subtheme": "matein1",
    "chunk_number": 1,
    "position_in_chunk": 13
  },
  {
    "lichess_id": "003YF",
    "fen": "r4rk1/1pp2ppp/p2p4/2bPp3/2P1Pn1q/P1N2B2/1P3P2/R1BQK1R1 w Q - 1 15",
    "solution_move": "c1f4",
    "full_solution": "c1f4 h4f2",
    "subtheme": "matein1",
    "chunk_number": 1,
    "position_in_chunk": 14
  },
  {
    "lichess_id": "00465",
    "fen": "3r1Q1k/pp4pp/2p5/6q1/5R2/2P5/P1P2PPP/3rR1K1 b - - 8 27",
    "solution_move": "d8f8",
    "full_solution": "d8f8 f4f8",
    "subtheme": "matein1",
    "chunk_number": 1,
    "position_in_chunk": 15
  },
  {
    "lichess_id": "004JD",
    "fen": "3r4/R7/2p5/p1P2p2/1p4k1/nP6/P2KNP2/8 w - - 3 41",
    "solution_move": "d2e3",
    "full_solution": "d2e3 a3c2",
    "subtheme": "matein1",
    "chunk_number": 1,
    "position_in_chunk": 16
  },
  {
    "lichess_id": "004WZ",
    "fen": "r6k/1b3pp1/p1q1pn1p/2p5/P1B5/1PN4Q/2P1RP1P/R4Kr1 w - - 2 26",
    "solution_move": "f1g1",
    "full_solution": "f1g1 c6h1",
    "subtheme": "matein1",
    "chunk_number": 1,
    "position_in_chunk": 17
  },
  {
    "lichess_id": "004iZ",
    "fen": "r2r2k1/2q1bpp1/3p1n1p/1ppN4/1P1BP3/P5Q1/4RPPP/R5K1 b - - 1 20",
    "solution_move": "f6d5",
    "full_solution": "f6d5 g3g7",
    "subtheme": "matein1",
    "chunk_number": 1,
    "position_in_chunk": 18
  },
  {
    "lichess_id": "004zI",
    "fen": "2q3k1/4br1p/6RQ/1p1n2p1/7P/1P4P1/1B2PP2/6K1 b - - 0 27",
    "solution_move": "h7g6",
    "full_solution": "h7g6 h6h8",
    "subtheme": "matein1",
    "chunk_number": 1,
    "position_in_chunk": 19
  },
  {
    "lichess_id": "005Ep",
    "fen": "5kr1/ppR3p1/3R3p/8/1r1n4/8/1P3PPP/2K5 b - - 4 31",
    "solution_move": "d4b5",
    "full_solution": "d4b5 d6d8",
    "subtheme": "matein1",
    "chunk_number": 1,
    "position_in_chunk": 20
  },
  {
    "lichess_id": "005wJ",
    "fen": "r3kb1r/ppqn1ppp/4pn2/1Q2Nb2/3P4/8/PP2PPPP/RNB1KB1R w KQkq - 4 9",
    "solution_move": "e5d7",
    "full_solution": "e5d7 c7c1",
    "subtheme": "matein1",
    "chunk_number": 1,
    "position_in_chunk": 21
  },
  {
    "lichess_id": "005x9",
    "fen": "r1b1kb1Q/ppp4p/6pB/3P4/2pn4/8/PPP1qPPP/RN1K3R w q - 2 13",
    "solution_move": "d1c1",
    "full_solution": "d1c1 e2c2",
    "subtheme": "matein1",
    "chunk_number": 1,
    "position_in_chunk": 22
  },
  {
    "lichess_id": "00656",
    "fen": "7r/ppp2kp1/2nb1pp1/3p3r/3P2q1/2PQB2P/PP3PP1/R3R1K1 w - - 0 18",
    "solution_move": "h3g4",
    "full_solution": "h3g4 h5h1",
    "subtheme": "matein1",
    "chunk_number": 1,
    "position_in_chunk": 23
  },
  {
    "lichess_id": "006GK",
    "fen": "2kr1br1/ppBb1ppp/8/3P2Q1/3n2n1/5N2/PP3qPP/RN2R2K b - - 0 16",
    "solution_move": "d4f3",
    "full_solution": "d4f3 g5d8",
    "subtheme": "matein1",
    "chunk_number": 1,
    "position_in_chunk": 24
  },
  {
    "lichess_id": "007AH",
    "fen": "3r1n2/1bp1bkpp/p1q2n2/1p6/3P4/P1N3B1/1PP2PPP/R2QR1K1 w - - 5 18",
    "solution_move": "d1e2",
    "full_solution": "d1e2 c6g2",
    "subtheme": "matein1",
    "chunk_number": 1,
    "position_in_chunk": 25
  },
  {
    "lichess_id": "007HB",
    "fen": "rn2q1k1/pp3ppp/2pb4/3p1B2/2Pn4/1Q3N2/PP3PPP/R1B4K w - - 0 15",
    "solution_move": "f3d4",
    "full_solution": "f3d4 e8e1",
    "subtheme": "matein1",
    "chunk_number": 1,
    "position_in_chunk": 26
  },
  {
    "lichess_id": "007QU",
    "fen": "2rq1rk1/1b3p1p/p3p3/1p1pB1p1/2nP2N1/1RP1PP2/P1Q3PP/3R2K1 b - - 1 22",
    "solution_move": "f7f5",
    "full_solution": "f7f5 g4h6",
    "subtheme": "matein1",
    "chunk_number": 1,
    "position_in_chunk": 27
  },
  {
    "lichess_id": "007c6",
    "fen": "2kr3r/pp1n2pp/2QB1bp1/5q2/2B5/8/PPP2PPP/3R1RK1 b - - 0 17",
    "solution_move": "b7c6",
    "full_solution": "b7c6 c4a6",
    "subtheme": "matein1",
    "chunk_number": 1,
    "position_in_chunk": 28
  },
  {
    "lichess_id": "007fJ",
    "fen": "8/1P3ppp/8/8/8/2pk3P/3p2P1/3K4 w - - 0 52",
    "solution_move": "b7b8q",
    "full_solution": "b7b8q c3c2",
    "subtheme": "matein1",
    "chunk_number": 1,
    "position_in_chunk": 29
  },
  {
    "lichess_id": "0082f",
    "fen": "r4rk1/2q2ppp/3pp3/4Pb1N/pp6/1B4Q1/PPP3PP/1K1RR3 b - - 0 21",
    "solution_move": "a4b3",
    "full_solution": "a4b3 g3g7",
    "subtheme": "matein1",
    "chunk_number": 1,
    "position_in_chunk": 30
  }
]